mc_coppel/__init__.py
mc_coppel-4.1.3.dist-info/METADATA
mc_coppel-4.1.3.dist-info/RECORD
mc_coppel-4.1.3.dist-info/WHEEL
mc_coppel-4.1.3.dist-info/top_level.txt
