Metadata-Version: 2.1
Name: mc-coppel
Version: 4.1.3
Summary: libreria para hacer la conexion de microservicios
Home-page: UNKNOWN
Author: Sergio Jimenez
Author-email: menine77@gmail.com
License: UNKNOWN
Platform: UNKNOWN
Classifier: Programming Language :: Python :: 3
Requires-Dist: simplejson (==3.16.0)
Requires-Dist: pymongo (==3.7.2)
Requires-Dist: kafka (==1.3.5)
Requires-Dist: requests (==2.20.0)
Requires-Dist: aiokafka (==0.4.2)
Requires-Dist: uuid (==1.30)
Requires-Dist: colorama (==0.4.0)
Requires-Dist: mongoengine (==0.15.3)
Requires-Dist: geopy (==1.17.0)
Requires-Dist: jsonmerge (==1.5.1)
